README.md
setup.cfg
setup.py
discord/__init__.py
discord/async_client.py
discord/async_socket.py
discord/client.py
discord/socket.py
discord/utils/__init__.py
discord/utils/exceptions.py
discord/utils/objects.py
discord/utils/requester.py
python_discord_api.egg-info/PKG-INFO
python_discord_api.egg-info/SOURCES.txt
python_discord_api.egg-info/dependency_links.txt
python_discord_api.egg-info/requires.txt
python_discord_api.egg-info/top_level.txt