Metadata-Version: 2.1
Name: python-discord-api
Version: 1.1
Summary: Library for creating discord bots and scripts.
Home-page: https://github.com/xXxCLOTIxXx/discord
Author: Xsarz
Author-email: xsarzy@gmail.com
License: MIT
Download-URL: https://github.com/xXxCLOTIxXx/discord/archive/refs/heads/main.zip
Keywords: discord.py,discord,discord-py,discord-bot,api,python,python3,python3.x,xsarz,official,sync,async
Platform: UNKNOWN
